odoo/addons/storage_image_import/README.rst
odoo/addons/storage_image_import/__init__.py
odoo/addons/storage_image_import/__manifest__.py
odoo/addons/storage_image_import/i18n/storage_image_import.pot
odoo/addons/storage_image_import/models/__init__.py
odoo/addons/storage_image_import/models/image_relation_abstract.py
odoo/addons/storage_image_import/models/storage_image.py
odoo/addons/storage_image_import/readme/CONTRIBUTORS.rst
odoo/addons/storage_image_import/readme/DESCRIPTION.rst
odoo/addons/storage_image_import/readme/USAGE.rst
odoo/addons/storage_image_import/static/description/icon.png
odoo/addons/storage_image_import/static/description/index.html
odoo/addons/storage_image_import/tests/__init__.py
odoo/addons/storage_image_import/tests/test_import.py
odoo/addons/storage_image_import/tests/models/__init__.py
odoo/addons/storage_image_import/tests/models/fake_image_relation.py
odoo/addons/storage_image_import/tests/static/akretion-logo.png
odoo/addons/storage_image_import/tests/static/oca-logo.png
odoo_addon_storage_image_import-15.0.1.0.0.2.dist-info/METADATA
odoo_addon_storage_image_import-15.0.1.0.0.2.dist-info/WHEEL
odoo_addon_storage_image_import-15.0.1.0.0.2.dist-info/top_level.txt
odoo_addon_storage_image_import-15.0.1.0.0.2.dist-info/RECORD
